lantern_flask/__init__.py
lantern_flask/controllers/__init__.py
lantern_flask/controllers/application_controller.py
lantern_flask/controllers/cognito_controller.py
lantern_flask/controllers/dynamo_controller.py
lantern_flask/controllers/fileupload_controller.py
lantern_flask/flask/__init__.py
lantern_flask/flask/api.py
lantern_flask/flask/flask_factory.py
lantern_flask/flask/router.py
lantern_flask/utils/__init__.py
lantern_flask/utils/dynamo.py
lantern_flask/utils/json.py
lantern_flask/utils/request.py
lantern_flask/utils/time.py
lantern_flask-0.0.47.dist-info/METADATA
lantern_flask-0.0.47.dist-info/WHEEL
lantern_flask-0.0.47.dist-info/top_level.txt
lantern_flask-0.0.47.dist-info/RECORD
